{
  "dailyReadData": {
    "1762054752245": {
      "filePath": "",
      "openCount": 0,
      "fileId": "1762054752245",
      "duration": 6000
    },
    "1766675074511": {
      "filePath": "",
      "openCount": 0,
      "fileId": "1766675074511",
      "duration": 222000
    },
    "1762452488137": {
      "filePath": "",
      "openCount": 0,
      "fileId": "1762452488137",
      "duration": 30000
    },
    "1766390445134": {
      "filePath": "",
      "openCount": 0,
      "fileId": "1766390445134",
      "duration": 36000
    },
    "1763955370872": {
      "filePath": "",
      "openCount": 0,
      "fileId": "1763955370872",
      "duration": 456000
    },
    "1766561770786": {
      "filePath": "",
      "openCount": 0,
      "fileId": "1766561770786",
      "duration": 6000
    },
    "undefined": {
      "filePath": "",
      "openCount": 0,
      "duration": 12000
    },
    "1761230158669": {
      "filePath": "",
      "openCount": 0,
      "fileId": "1761230158669",
      "duration": 66000
    },
    "1761230164610": {
      "filePath": "",
      "openCount": 0,
      "fileId": "1761230164610",
      "duration": 18000
    },
    "1761230157333": {
      "filePath": "",
      "openCount": 0,
      "fileId": "1761230157333",
      "duration": 18000
    },
    "1766728645936": {
      "filePath": "",
      "openCount": 0,
      "fileId": "1766728645936",
      "duration": 6000
    },
    "1763448908714": {
      "filePath": "",
      "openCount": 0,
      "fileId": "1763448908714",
      "duration": 12000
    },
    "1762270348060": {
      "filePath": "",
      "openCount": 0,
      "fileId": "1762270348060",
      "duration": 6000
    }
  }
}