{
  "dailyReadData": {
    "1777725601714": {
      "filePath": "",
      "openCount": 0,
      "fileId": "1777725601714",
      "duration": 1776000
    },
    "1774061982690": {
      "filePath": "",
      "openCount": 0,
      "fileId": "1774061982690",
      "duration": 588000
    },
    "1764728425872": {
      "filePath": "",
      "openCount": 0,
      "fileId": "1764728425872",
      "duration": 96000
    },
    "1776604964966": {
      "filePath": "",
      "openCount": 0,
      "fileId": "1776604964966",
      "duration": 12000
    },
    "1776049560807": {
      "filePath": "",
      "openCount": 0,
      "fileId": "1776049560807",
      "duration": 48000
    },
    "1776150844353": {
      "filePath": "",
      "openCount": 0,
      "fileId": "1776150844353",
      "duration": 156000
    },
    "1777427691363": {
      "filePath": "",
      "openCount": 0,
      "fileId": "1777427691363",
      "duration": 12000
    },
    "1777770569489": {
      "filePath": "",
      "openCount": 0,
      "fileId": "1777770569489",
      "duration": 6000
    },
    "1776563399102": {
      "filePath": "",
      "openCount": 0,
      "fileId": "1776563399102",
      "duration": 24000
    },
    "1776151029528": {
      "filePath": "",
      "openCount": 0,
      "fileId": "1776151029528",
      "duration": 6000
    },
    "1777685558791": {
      "filePath": "",
      "openCount": 0,
      "fileId": "1777685558791",
      "duration": 282000
    },
    "undefined": {
      "filePath": "",
      "openCount": 0,
      "duration": 144000
    },
    "1777771018986": {
      "filePath": "",
      "openCount": 0,
      "fileId": "1777771018986",
      "duration": 42000
    },
    "1762270348060": {
      "filePath": "",
      "openCount": 0,
      "fileId": "1762270348060",
      "duration": 798000
    },
    "1777771379017": {
      "filePath": "",
      "openCount": 0,
      "fileId": "1777771379017",
      "duration": 30000
    },
    "1777771499027": {
      "filePath": "",
      "openCount": 0,
      "fileId": "1777771499027",
      "duration": 12000
    },
    "1777771517345": {
      "filePath": "",
      "openCount": 0,
      "fileId": "1777771517345",
      "duration": 1992000
    },
    "1777641119055": {
      "filePath": "",
      "openCount": 0,
      "fileId": "1777641119055",
      "duration": 18000
    },
    "1761667459607": {
      "filePath": "",
      "openCount": 0,
      "fileId": "1761667459607",
      "duration": 48000
    },
    "1777772711121": {
      "filePath": "",
      "openCount": 0,
      "fileId": "1777772711121",
      "duration": 60000
    },
    "1777772729123": {
      "filePath": "",
      "openCount": 0,
      "fileId": "1777772729123",
      "duration": 216000
    },
    "1777772951950": {
      "filePath": "",
      "openCount": 0,
      "fileId": "1777772951950",
      "duration": 54000
    },
    "1777726870059": {
      "filePath": "",
      "openCount": 0,
      "fileId": "1777726870059",
      "duration": 18000
    },
    "1777727188065": {
      "filePath": "",
      "openCount": 0,
      "fileId": "1777727188065",
      "duration": 12000
    },
    "1777774133185": {
      "filePath": "",
      "openCount": 0,
      "fileId": "1777774133185",
      "duration": 24000
    },
    "1777788341257": {
      "filePath": "",
      "openCount": 0,
      "fileId": "1777788341257",
      "duration": 30000
    },
    "1777788377439": {
      "filePath": "",
      "openCount": 0,
      "fileId": "1777788377439",
      "duration": 30000
    },
    "1777788413266": {
      "filePath": "",
      "openCount": 0,
      "fileId": "1777788413266",
      "duration": 12000
    },
    "1777788432206": {
      "filePath": "",
      "openCount": 0,
      "fileId": "1777788432206",
      "duration": 882000
    },
    "1777789379248": {
      "filePath": "",
      "openCount": 0,
      "fileId": "1777789379248",
      "duration": 672000
    },
    "1777789774283": {
      "filePath": "",
      "openCount": 0,
      "fileId": "1777789774283",
      "duration": 6000
    },
    "1777192062878": {
      "filePath": "",
      "openCount": 0,
      "fileId": "1777192062878",
      "duration": 30000
    },
    "1775180716793": {
      "filePath": "",
      "openCount": 0,
      "fileId": "1775180716793",
      "duration": 156000
    },
    "1777791193481": {
      "filePath": "",
      "openCount": 0,
      "fileId": "1777791193481",
      "duration": 222000
    },
    "1777791427463": {
      "filePath": "",
      "openCount": 0,
      "fileId": "1777791427463",
      "duration": 6000
    },
    "1777614641281": {
      "filePath": "",
      "openCount": 0,
      "fileId": "1777614641281",
      "duration": 162000
    },
    "1777520032459": {
      "filePath": "",
      "openCount": 0,
      "fileId": "1777520032459",
      "duration": 12000
    },
    "1777791811462": {
      "filePath": "",
      "openCount": 0,
      "fileId": "1777791811462",
      "duration": 12000
    },
    "1777795411449": {
      "filePath": "",
      "openCount": 0,
      "fileId": "1777795411449",
      "duration": 186000
    },
    "1761207353733": {
      "filePath": "",
      "openCount": 0,
      "fileId": "1761207353733",
      "duration": 192000
    },
    "1761219862925": {
      "filePath": "",
      "openCount": 0,
      "fileId": "1761219862925",
      "duration": 174000
    },
    "1767929233062": {
      "filePath": "",
      "openCount": 0,
      "fileId": "1767929233062",
      "duration": 372000
    },
    "1777024344181": {
      "filePath": "",
      "openCount": 0,
      "fileId": "1777024344181",
      "duration": 78000
    },
    "1777798747438": {
      "filePath": "",
      "openCount": 0,
      "fileId": "1777798747438",
      "duration": 6000
    },
    "1776405532819": {
      "filePath": "",
      "openCount": 0,
      "fileId": "1776405532819",
      "duration": 108000
    },
    "1777726300066": {
      "filePath": "",
      "openCount": 0,
      "fileId": "1777726300066",
      "duration": 1806000
    },
    "1776407926959": {
      "filePath": "",
      "openCount": 0,
      "fileId": "1776407926959",
      "duration": 240000
    },
    "1777802609445": {
      "filePath": "",
      "openCount": 0,
      "fileId": "1777802609445",
      "duration": 6000
    },
    "1776407950800": {
      "filePath": "",
      "openCount": 0,
      "fileId": "1776407950800",
      "duration": 12000
    },
    "1777190220893": {
      "filePath": "",
      "openCount": 0,
      "fileId": "1777190220893",
      "duration": 510000
    },
    "1777807315385": {
      "filePath": "",
      "openCount": 0,
      "fileId": "1777807315385",
      "duration": 36000
    },
    "1774676360564": {
      "filePath": "",
      "openCount": 0,
      "fileId": "1774676360564",
      "duration": 6000
    },
    "1775491626622": {
      "filePath": "",
      "openCount": 0,
      "fileId": "1775491626622",
      "duration": 6000
    },
    "1774188643156": {
      "filePath": "",
      "openCount": 0,
      "fileId": "1774188643156",
      "duration": 24000
    },
    "1777614263215": {
      "filePath": "",
      "openCount": 0,
      "fileId": "1777614263215",
      "duration": 6000
    },
    "1777808851184": {
      "filePath": "",
      "openCount": 0,
      "fileId": "1777808851184",
      "duration": 318000
    },
    "1777813897179": {
      "filePath": "",
      "openCount": 0,
      "fileId": "1777813897179",
      "duration": 72000
    }
  }
}