{
  "dailyReadData": {
    "1762053846248": {
      "filePath": "",
      "openCount": 0,
      "fileId": "1762053846248",
      "duration": 150000
    },
    "1766994975871": {
      "filePath": "",
      "openCount": 0,
      "fileId": "1766994975871",
      "duration": 30000
    },
    "1762053096241": {
      "filePath": "",
      "openCount": 0,
      "fileId": "1762053096241",
      "duration": 6000
    },
    "undefined": {
      "filePath": "",
      "openCount": 0,
      "duration": 276000
    },
    "1768351104857": {
      "filePath": "",
      "openCount": 0,
      "fileId": "1768351104857",
      "duration": 24000
    },
    "1768351134540": {
      "filePath": "",
      "openCount": 0,
      "fileId": "1768351134540",
      "duration": 84000
    },
    "1767056759236": {
      "filePath": "",
      "openCount": 0,
      "fileId": "1767056759236",
      "duration": 6000
    },
    "1767767801507": {
      "filePath": "",
      "openCount": 0,
      "fileId": "1767767801507",
      "duration": 240000
    },
    "1766999841224": {
      "filePath": "",
      "openCount": 0,
      "fileId": "1766999841224",
      "duration": 18000
    },
    "1762150582210": {
      "filePath": "",
      "openCount": 0,
      "fileId": "1762150582210",
      "duration": 24000
    },
    "1765112724465": {
      "filePath": "",
      "openCount": 0,
      "fileId": "1765112724465",
      "duration": 30000
    },
    "1768351614540": {
      "filePath": "",
      "openCount": 0,
      "fileId": "1768351614540",
      "duration": 6000
    },
    "1762277311537": {
      "filePath": "",
      "openCount": 0,
      "fileId": "1762277311537",
      "duration": 900000
    },
    "1764825501189": {
      "filePath": "",
      "openCount": 0,
      "fileId": "1764825501189",
      "duration": 42000
    },
    "1768351680539": {
      "filePath": "",
      "openCount": 0,
      "fileId": "1768351680539",
      "duration": 90000
    },
    "1762452488137": {
      "filePath": "",
      "openCount": 0,
      "fileId": "1762452488137",
      "duration": 828000
    },
    "1766388285145": {
      "filePath": "",
      "openCount": 0,
      "fileId": "1766388285145",
      "duration": 174000
    },
    "1766992465874": {
      "filePath": "",
      "openCount": 0,
      "fileId": "1766992465874",
      "duration": 48000
    },
    "1768352394535": {
      "filePath": "",
      "openCount": 0,
      "fileId": "1768352394535",
      "duration": 18000
    },
    "1767061991228": {
      "filePath": "",
      "openCount": 0,
      "fileId": "1767061991228",
      "duration": 1380000
    },
    "1761400945025": {
      "filePath": "",
      "openCount": 0,
      "fileId": "1761400945025",
      "duration": 18000
    },
    "1764404692094": {
      "filePath": "",
      "openCount": 0,
      "fileId": "1764404692094",
      "duration": 78000
    },
    "1764001415080": {
      "filePath": "",
      "openCount": 0,
      "fileId": "1764001415080",
      "duration": 36000
    },
    "1765011565029": {
      "filePath": "",
      "openCount": 0,
      "fileId": "1765011565029",
      "duration": 36000
    },
    "1768352742557": {
      "filePath": "",
      "openCount": 0,
      "fileId": "1768352742557",
      "duration": 6000
    },
    "1765246931116": {
      "filePath": "",
      "openCount": 0,
      "fileId": "1765246931116",
      "duration": 24000
    },
    "1768317337940": {
      "filePath": "",
      "openCount": 0,
      "fileId": "1768317337940",
      "duration": 1392000
    },
    "1762277339105": {
      "filePath": "",
      "openCount": 0,
      "fileId": "1762277339105",
      "duration": 498000
    },
    "1762278970061": {
      "filePath": "",
      "openCount": 0,
      "fileId": "1762278970061",
      "duration": 6000
    },
    "1761183381637": {
      "filePath": "",
      "openCount": 0,
      "fileId": "1761183381637",
      "duration": 96000
    },
    "1768353090537": {
      "filePath": "",
      "openCount": 0,
      "fileId": "1768353090537",
      "duration": 324000
    },
    "1768353240593": {
      "filePath": "",
      "openCount": 0,
      "fileId": "1768353240593",
      "duration": 72000
    },
    "1768353462535": {
      "filePath": "",
      "openCount": 0,
      "fileId": "1768353462535",
      "duration": 78000
    },
    "1761881040835": {
      "filePath": "",
      "openCount": 0,
      "fileId": "1761881040835",
      "duration": 66000
    },
    "1761881096130": {
      "filePath": "",
      "openCount": 0,
      "fileId": "1761881096130",
      "duration": 18000
    },
    "1768354554770": {
      "filePath": "",
      "openCount": 0,
      "fileId": "1768354554770",
      "duration": 36000
    },
    "1768354614534": {
      "filePath": "",
      "openCount": 0,
      "fileId": "1768354614534",
      "duration": 24000
    },
    "1768354752536": {
      "filePath": "",
      "openCount": 0,
      "fileId": "1768354752536",
      "duration": 72000
    },
    "1768354896757": {
      "filePath": "",
      "openCount": 0,
      "fileId": "1768354896757",
      "duration": 186000
    },
    "1768355178536": {
      "filePath": "",
      "openCount": 0,
      "fileId": "1768355178536",
      "duration": 234000
    },
    "1768355634544": {
      "filePath": "",
      "openCount": 0,
      "fileId": "1768355634544",
      "duration": 144000
    },
    "1765381861348": {
      "filePath": "",
      "openCount": 0,
      "fileId": "1765381861348",
      "duration": 78000
    },
    "1768356090538": {
      "filePath": "",
      "openCount": 0,
      "fileId": "1768356090538",
      "duration": 6000
    },
    "1765382119338": {
      "filePath": "",
      "openCount": 0,
      "fileId": "1765382119338",
      "duration": 6000
    },
    "1766990347885": {
      "filePath": "",
      "openCount": 0,
      "fileId": "1766990347885",
      "duration": 108000
    },
    "1767922285060": {
      "filePath": "",
      "openCount": 0,
      "fileId": "1767922285060",
      "duration": 102000
    },
    "1767516751653": {
      "filePath": "",
      "openCount": 0,
      "fileId": "1767516751653",
      "duration": 6000
    },
    "1762396661996": {
      "filePath": "",
      "openCount": 0,
      "fileId": "1762396661996",
      "duration": 570000
    },
    "1761878029356": {
      "filePath": "",
      "openCount": 0,
      "fileId": "1761878029356",
      "duration": 18000
    },
    "1765248887217": {
      "filePath": "",
      "openCount": 0,
      "fileId": "1765248887217",
      "duration": 24000
    },
    "1765347203173": {
      "filePath": "",
      "openCount": 0,
      "fileId": "1765347203173",
      "duration": 120000
    },
    "1761697803004": {
      "filePath": "",
      "openCount": 0,
      "fileId": "1761697803004",
      "duration": 126000
    },
    "1768362053384": {
      "filePath": "",
      "openCount": 0,
      "fileId": "1768362053384",
      "duration": 6000
    },
    "1768362065879": {
      "filePath": "",
      "openCount": 0,
      "fileId": "1768362065879",
      "duration": 12000
    },
    "1768362089563": {
      "filePath": "",
      "openCount": 0,
      "fileId": "1768362089563",
      "duration": 66000
    },
    "1768362167388": {
      "filePath": "",
      "openCount": 0,
      "fileId": "1768362167388",
      "duration": 60000
    },
    "1762158176414": {
      "filePath": "",
      "openCount": 0,
      "fileId": "1762158176414",
      "duration": 198000
    },
    "1762452404685": {
      "filePath": "",
      "openCount": 0,
      "fileId": "1762452404685",
      "duration": 60000
    },
    "1768362203406": {
      "filePath": "",
      "openCount": 0,
      "fileId": "1768362203406",
      "duration": 6000
    },
    "1768373957968": {
      "filePath": "",
      "openCount": 0,
      "fileId": "1768373957968",
      "duration": 18000
    },
    "1768373981385": {
      "filePath": "",
      "openCount": 0,
      "fileId": "1768373981385",
      "duration": 48000
    },
    "1768374155385": {
      "filePath": "",
      "openCount": 0,
      "fileId": "1768374155385",
      "duration": 252000
    },
    "1768374227392": {
      "filePath": "",
      "openCount": 0,
      "fileId": "1768374227392",
      "duration": 12000
    },
    "1768374246969": {
      "filePath": "",
      "openCount": 0,
      "fileId": "1768374246969",
      "duration": 18000
    },
    "1768374269728": {
      "filePath": "",
      "openCount": 0,
      "fileId": "1768374269728",
      "duration": 6000
    },
    "1768374281387": {
      "filePath": "",
      "openCount": 0,
      "fileId": "1768374281387",
      "duration": 78000
    },
    "1764298538138": {
      "filePath": "",
      "openCount": 0,
      "fileId": "1764298538138",
      "duration": 48000
    },
    "1768376972752": {
      "filePath": "",
      "openCount": 0,
      "fileId": "1768376972752",
      "duration": 258000
    },
    "1767918925782": {
      "filePath": "",
      "openCount": 0,
      "fileId": "1767918925782",
      "duration": 66000
    },
    "1761463980787": {
      "filePath": "",
      "openCount": 0,
      "fileId": "1761463980787",
      "duration": 6000
    },
    "1767605497859": {
      "filePath": "",
      "openCount": 0,
      "fileId": "1767605497859",
      "duration": 54000
    },
    "1768382276749": {
      "filePath": "",
      "openCount": 0,
      "fileId": "1768382276749",
      "duration": 6000
    },
    "1768392211206": {
      "filePath": "",
      "openCount": 0,
      "fileId": "1768392211206",
      "duration": 90000
    },
    "1767488210547": {
      "filePath": "",
      "openCount": 0,
      "fileId": "1767488210547",
      "duration": 6000
    },
    "1767488209024": {
      "filePath": "",
      "openCount": 0,
      "fileId": "1767488209024",
      "duration": 54000
    },
    "1768392361090": {
      "filePath": "",
      "openCount": 0,
      "fileId": "1768392361090",
      "duration": 102000
    },
    "1768392499088": {
      "filePath": "",
      "openCount": 0,
      "fileId": "1768392499088",
      "duration": 24000
    },
    "1768392565090": {
      "filePath": "",
      "openCount": 0,
      "fileId": "1768392565090",
      "duration": 36000
    },
    "1763300728559": {
      "filePath": "",
      "openCount": 0,
      "fileId": "1763300728559",
      "duration": 12000
    },
    "1762270348060": {
      "filePath": "",
      "openCount": 0,
      "fileId": "1762270348060",
      "duration": 42000
    },
    "1766834976472": {
      "filePath": "",
      "openCount": 0,
      "fileId": "1766834976472",
      "duration": 18000
    },
    "1767921859059": {
      "filePath": "",
      "openCount": 0,
      "fileId": "1767921859059",
      "duration": 42000
    },
    "1768392919088": {
      "filePath": "",
      "openCount": 0,
      "fileId": "1768392919088",
      "duration": 66000
    },
    "1768393069090": {
      "filePath": "",
      "openCount": 0,
      "fileId": "1768393069090",
      "duration": 12000
    },
    "1767057629305": {
      "filePath": "",
      "openCount": 0,
      "fileId": "1767057629305",
      "duration": 174000
    },
    "1761723476543": {
      "filePath": "",
      "openCount": 0,
      "fileId": "1761723476543",
      "duration": 6000
    },
    "1762389977842": {
      "filePath": "",
      "openCount": 0,
      "fileId": "1762389977842",
      "duration": 6000
    },
    "1765017205222": {
      "filePath": "",
      "openCount": 0,
      "fileId": "1765017205222",
      "duration": 6000
    },
    "1768272722780": {
      "filePath": "",
      "openCount": 0,
      "fileId": "1768272722780",
      "duration": 24000
    },
    "1768393855336": {
      "filePath": "",
      "openCount": 0,
      "fileId": "1768393855336",
      "duration": 18000
    },
    "1768393903091": {
      "filePath": "",
      "openCount": 0,
      "fileId": "1768393903091",
      "duration": 30000
    },
    "1768394233101": {
      "filePath": "",
      "openCount": 0,
      "fileId": "1768394233101",
      "duration": 126000
    },
    "1768401555622": {
      "filePath": "",
      "openCount": 0,
      "fileId": "1768401555622",
      "duration": 1056000
    },
    "1768402905621": {
      "filePath": "",
      "openCount": 0,
      "fileId": "1768402905621",
      "duration": 24000
    },
    "1761132405612": {
      "filePath": "",
      "openCount": 0,
      "fileId": "1761132405612",
      "duration": 120000
    },
    "1763954894498": {
      "filePath": "",
      "openCount": 0,
      "fileId": "1763954894498",
      "duration": 12000
    },
    "1761409585017": {
      "filePath": "",
      "openCount": 0,
      "fileId": "1761409585017",
      "duration": 144000
    },
    "1768404789625": {
      "filePath": "",
      "openCount": 0,
      "fileId": "1768404789625",
      "duration": 84000
    }
  }
}